Metadata-Version: 2.1
Name: tensorleap
Version: 0.0.4
Summary: Generates equal keras models with the desired data format
Home-page: https://github.com/tensorleap/keras-data-format-converter
Author: Doron Har Noy
Author-email: doron.harnoy@tensorleap.ai
License: MIT
Keywords: machine-learning deep-learning keras neural-network tensorflow vgg resnet tensorleap
Platform: UNKNOWN
Classifier: Development Status :: 3 - Alpha
Classifier: Intended Audience :: Science/Research
Classifier: License :: OSI Approved :: MIT License
Classifier: Operating System :: OS Independent
Classifier: Programming Language :: Python
Classifier: Topic :: Scientific/Engineering :: Image Recognition
